MANIFEST.in
README.md
requirements.txt
setup.py
feather/__init__.py
feather/api.py
feather/compat.py
feather/ext.cpp
feather/ext.pyx
feather/interop.h
feather/libfeather.pxd
feather/version.py
feather/tests/__init__.py
feather/tests/test_reader.py
feather_format.egg-info/PKG-INFO
feather_format.egg-info/SOURCES.txt
feather_format.egg-info/dependency_links.txt
feather_format.egg-info/requires.txt
feather_format.egg-info/top_level.txt
src/feather/CMakeLists.txt
src/feather/api.h
src/feather/buffer.cc
src/feather/buffer.h
src/feather/buffer.o
src/feather/common.h
src/feather/compatibility.h
src/feather/feather-c.cc
src/feather/feather-c.h
src/feather/feather-c.o
src/feather/io.cc
src/feather/io.h
src/feather/io.o
src/feather/metadata.cc
src/feather/metadata.fbs
src/feather/metadata.h
src/feather/metadata.o
src/feather/metadata_generated.h
src/feather/mman.h
src/feather/reader.cc
src/feather/reader.h
src/feather/reader.o
src/feather/status.cc
src/feather/status.h
src/feather/status.o
src/feather/types.cc
src/feather/types.h
src/feather/types.o
src/feather/writer.cc
src/feather/writer.h
src/feather/writer.o
src/feather/tests/c-api-test.cc
src/feather/tests/io-test.cc
src/feather/tests/metadata-test.cc
src/feather/tests/test-common.h
src/feather/tests/test_main.cc
src/feather/tests/writer-test.cc
src/flatbuffers/flatbuffers.h