Metadata-Version: 1.1
Name: feather-format
Version: 0.3.1
Summary: Python interface to the Apache Arrow-based Feather File Format
Home-page: http://github.com/wesm/feather
Author: Wes McKinney
Author-email: wesm@apache.org
License: Apache License, Version 2.0
Platform: UNKNOWN
Classifier: Development Status :: 3 - Alpha
Classifier: Environment :: Console
Classifier: Programming Language :: Python
Classifier: Programming Language :: Python :: 2
Classifier: Programming Language :: Python :: 3
Classifier: Programming Language :: Python :: 2.7
Classifier: Programming Language :: Python :: 3.4
Classifier: Programming Language :: Python :: 3.5
Classifier: Programming Language :: Cython
